compyner/__init__.py
compyner/__main__.py
compyner/engine.py
compyner/logging.py
compyner/snippets/__init__.py
compyner/snippets/module.py
compyner/typehints.py
compyner-0.3.1.dist-info/entry_points.txt
compyner-0.3.1.dist-info/METADATA
compyner-0.3.1.dist-info/WHEEL
compyner-0.3.1.dist-info/RECORD
