Metadata-Version: 2.3
Name: compyner
Version: 0.3.1
Summary: A small tool to bundle a python file and all its imports into a single file.
Author: J0J0HA aka. JoJoJux
Author-email: johannes@jojojux.de
Requires-Python: >=3.13.1,<4.0
Classifier: Programming Language :: Python :: 3
Requires-Dist: ast-comments (>=1.2.2,<2.0.0)
Project-URL: Repository, https://github.com/GSG-Robots/compyner
